tutorjupyter/__about__.py
tutorjupyter/__init__.py
tutorjupyter/plugin.py
tutorjupyter/patches/caddyfile
tutorjupyter/patches/local-docker-compose-jobs-services
tutorjupyter/patches/local-docker-compose-services
tutorjupyter/patches/nginx-extra
tutorjupyter/patches/openedx-dockerfile-post-python-requirements
tutorjupyter/patches/openedx-lms-production-settings
tutorjupyter/templates/jupyter/build/jupyter/Dockerfile
tutorjupyter/templates/jupyter/build/jupyter/jupyterhub_config.py
tutorjupyter/templates/jupyter/build/jupyter/requirements.txt
tutorjupyter/templates/jupyter/build/jupyter/user_list.txt
tutorjupyter/templates/jupyter/hooks/jupyter/init
tutorjupyter/templates/jupyter/hooks/lms/init
tutor_contrib_jupyter-0.2.0.dist-info/METADATA
tutor_contrib_jupyter-0.2.0.dist-info/WHEEL
tutor_contrib_jupyter-0.2.0.dist-info/entry_points.txt
tutor_contrib_jupyter-0.2.0.dist-info/top_level.txt
tutor_contrib_jupyter-0.2.0.dist-info/RECORD
